flaml/__init__.py
flaml/config.py
flaml/ml.py
flaml/version.py
flaml/autogen/__init__.py
flaml/autogen/code_utils.py
flaml/autogen/math_utils.py
flaml/autogen/retrieve_utils.py
flaml/autogen/agentchat/__init__.py
flaml/autogen/agentchat/agent.py
flaml/autogen/agentchat/assistant_agent.py
flaml/autogen/agentchat/conversable_agent.py
flaml/autogen/agentchat/groupchat.py
flaml/autogen/agentchat/user_proxy_agent.py
flaml/autogen/extensions/__init__.py
flaml/autogen/oai/__init__.py
flaml/autogen/oai/completion.py
flaml/autogen/oai/openai_utils.py
flaml/automl/__init__.py
flaml/automl/automl.py
flaml/automl/data.py
flaml/automl/logger.py
flaml/automl/ml.py
flaml/automl/model.py
flaml/automl/state.py
flaml/automl/training_log.py
flaml/automl/contrib/__init__.py
flaml/automl/contrib/histgb.py
flaml/automl/nlp/__init__.py
flaml/automl/nlp/utils.py
flaml/automl/nlp/huggingface/__init__.py
flaml/automl/nlp/huggingface/data_collator.py
flaml/automl/nlp/huggingface/trainer.py
flaml/automl/nlp/huggingface/training_args.py
flaml/automl/nlp/huggingface/utils.py
flaml/automl/spark/__init__.py
flaml/automl/spark/metrics.py
flaml/automl/spark/utils.py
flaml/automl/task/__init__.py
flaml/automl/task/factory.py
flaml/automl/task/generic_task.py
flaml/automl/task/task.py
flaml/automl/task/time_series_task.py
flaml/automl/time_series/__init__.py
flaml/automl/time_series/feature.py
flaml/automl/time_series/sklearn.py
flaml/automl/time_series/tcn.py
flaml/automl/time_series/tft.py
flaml/automl/time_series/ts_data.py
flaml/automl/time_series/ts_model.py
flaml/default/__init__.py
flaml/default/estimator.py
flaml/default/greedy.py
flaml/default/portfolio.py
flaml/default/regret.py
flaml/default/suggest.py
flaml/default/all/binary.json
flaml/default/all/multiclass.json
flaml/default/all/regression.json
flaml/default/extra_tree/binary.json
flaml/default/extra_tree/multiclass.json
flaml/default/extra_tree/regression.json
flaml/default/lgbm/binary.json
flaml/default/lgbm/multiclass.json
FLAML-2.3.6.dist-info/LICENSE
FLAML-2.3.6.dist-info/METADATA
FLAML-2.3.6.dist-info/NOTICE.md
FLAML-2.3.6.dist-info/WHEEL
FLAML-2.3.6.dist-info/top_level.txt
FLAML-2.3.6.dist-info/RECORD
