Metadata-Version: 2.1
Name: FLAML
Version: 2.3.6
Summary: A fast library for automated machine learning and tuning
Home-page: https://github.com/microsoft/FLAML
Author: Microsoft Corporation
Author-email: hpo@microsoft.com
Classifier: License :: OSI Approved :: MIT License
Classifier: Operating System :: OS Independent
Classifier: Programming Language :: Python :: 3
Classifier: Programming Language :: Python :: 3.9
Classifier: Programming Language :: Python :: 3.10
Classifier: Programming Language :: Python :: 3.11
Requires-Python: >=3.9
Provides-Extra: automl
Provides-Extra: notebook
Provides-Extra: spark
Provides-Extra: test
Provides-Extra: catboost
Provides-Extra: blendsearch
Provides-Extra: ray
Provides-Extra: azureml
Provides-Extra: nni
Provides-Extra: vw
Provides-Extra: hf
Provides-Extra: nlp
Provides-Extra: ts_forecast
Provides-Extra: forecast
Provides-Extra: benchmark
Provides-Extra: openai
Provides-Extra: autogen
Provides-Extra: mathchat
Provides-Extra: retrievechat
Provides-Extra: synapse
Provides-Extra: autozero
License-File: LICENSE
License-File: NOTICE.md
